<?xml version="1.0" encoding="UTF-8"?>
<databaseChangeLog
        xmlns="http://www.liquibase.org/xml/ns/dbchangelog"
        xmlns:xsi="http://www.w3.org/2001/XMLSchema-instance"
        xsi:schemaLocation="http://www.liquibase.org/xml/ns/dbchangelog
         http://www.liquibase.org/xml/ns/dbchangelog/dbchangelog-2.0.xsd">

    <changeSet id="1" author="jvelo">

        <!-- Configuration table -->
        <createTable tableName="configuration">
            <column name="id" type="bigint" autoIncrement="true">
                <constraints primaryKey="true" nullable="false"/>
            </column>
            <column name="version" type="smallint">
                <constraints nullable="false"/>
            </column>
            <column name="data" type="mediumtext"/>
        </createTable>

        <!-- Tenant table -->
        <createTable tableName="tenant">
            <column name="id" type="bigint" autoIncrement="true">
                <constraints primaryKey="true" nullable="false"/>
            </column>
            <column name="slug" type="varchar(255)">
                <constraints nullable="false" unique="true"/>
            </column>
            <column name="default_host" type="varchar(255)">
                <constraints unique="true"/>
            </column>
            <column name="configuration_id" type="bigint"/>
        </createTable>
        <addForeignKeyConstraint constraintName="TENANT_CONFIGURATION_FK"
                baseTableName="tenant" baseColumnNames="configuration_id"
                referencedTableName="configuration" referencedColumnNames="id"/>
        <createIndex tableName="tenant" indexName="TENANT_DEFAULT_HOST_INDEX">
            <column name="default_host"/>
        </createIndex>
        <createIndex tableName="tenant" indexName="TENANT_SLUG_INDEX">
            <column name="slug"/>
        </createIndex>

        <!-- Entity table -->
        <createTable tableName="entity">
            <column name="id" type="bigint" autoIncrement="true">
                <constraints primaryKey="true" nullable="false"/>
            </column>
            <column name="slug" type="varchar(255)">
                <constraints nullable="false"/>
            </column>
            <column name="type" type="varchar(255)">
                <constraints nullable="false"/>
            </column>
            <column name="tenant_id" type="bigint"/>
            <column name="parent_id" type="bigint"/>
        </createTable>
        <addUniqueConstraint tableName="entity" columnNames="slug,type,tenant_id"
                constraintName="ENTITY_UNIQUE_SLUG_PER_TYPE_PER_TENANT"/>
        <addForeignKeyConstraint constraintName="ENTITY_TENANT_FK"
                baseTableName="entity" baseColumnNames="tenant_id"
                referencedTableName="tenant" referencedColumnNames="id"/>
        <addForeignKeyConstraint constraintName="ENTITY_PARENT_FK"
                baseTableName="entity" baseColumnNames="parent_id"
                referencedTableName="entity" referencedColumnNames="id"/>
        <createIndex tableName="entity" indexName="ENTITY_SLUG_INDEX">
            <column name="slug"/>
        </createIndex>
        <createIndex tableName="entity" indexName="ENTITY_TYPE_INDEX">
            <column name="type"/>
        </createIndex>
        <createIndex tableName="entity" indexName="ENTITY_TENANT_INDEX">
            <column name="tenant_id"/>
        </createIndex>

        <!-- Addons -->
        <createTable tableName="addon">
            <column name="entity_id" type="bigint"/>
            <column name="source" type="varchar(255)"/>
            <column name="addon_group" type="varchar(255)"/>
            <!-- "group" is a reserved keyword -->
            <column name="type" type="varchar(255)"/>
            <column name="addon_key" type="varchar(255)"/>
            <!-- "key" is a reserved keyword -->
            <column name="value" type="varchar(2000)"/>
        </createTable>
        <addUniqueConstraint tableName="addon" columnNames="entity_id,source,addon_group,addon_key"
                constraintName="ADDON_UNIQUE_ADDON_KEY_PER_SOURCE_GROUP_ENTITY"/>
        <addForeignKeyConstraint constraintName="ADDON_ENTITY_FK"
                baseTableName="addon" baseColumnNames="entity_id"
                referencedTableName="entity" referencedColumnNames="id"/>
        <createIndex tableName="addon" indexName="ADDON_KEY_INDEX">
            <column name="addon_key"/>
        </createIndex>
        <createIndex tableName="addon" indexName="ADDON_SOURCE_INDEX">
            <column name="source"/>
        </createIndex>
        <createIndex tableName="addon" indexName="ADDON_GROUP_INDEX">
            <column name="addon_group"/>
        </createIndex>

        <!-- Translations -->
        <createTable tableName="translation">
            <column name="id" type="bigint" autoIncrement="true">
                <constraints primaryKey="true" nullable="false"/>
            </column>
            <column name="entity_id" type="bigint"/>
            <column name="field" type="varchar(255)"/>
        </createTable>
        <addUniqueConstraint tableName="translation" columnNames="entity_id,field"
                constraintName="TRANSLATION_UNIQUE_TRANSLATION_PER_FIELD_PER_ENTITY"/>
        <addForeignKeyConstraint constraintName="TRANSLATION_ENTITY_FK"
                baseTableName="translation" baseColumnNames="entity_id"
                referencedTableName="entity" referencedColumnNames="id"/>
        <createIndex tableName="translation" indexName="TRANSLATION_FIELD_INDEX">
            <column name="field"/>
        </createIndex>

        <createTable tableName="translation_small">
            <column name="id" type="bigint" autoIncrement="true">
                <constraints primaryKey="true" nullable="false"/>
            </column>
            <column name="translation_id" type="bigint"/>
            <column name="locale" type="varchar(255)"/>
            <column name="text" type="varchar(255)"/>
        </createTable>
        <addUniqueConstraint tableName="translation_small" columnNames="translation_id,locale"
                constraintName="TRANSLATION_SMALL_UNIQUE_TRANSLATION_PER_LANG"/>
        <addForeignKeyConstraint constraintName="TRANSLATION_SMALL_TRANSLATION_FK"
                baseTableName="translation_small" baseColumnNames="translation_id"
                referencedTableName="translation" referencedColumnNames="id"/>
        <createIndex tableName="translation_small" indexName="TRANSLATION_SMALL_LANG_INDEX">
            <column name="locale"/>
        </createIndex>

        <createTable tableName="translation_medium">
            <column name="id" type="bigint" autoIncrement="true">
                <constraints primaryKey="true" nullable="false"/>
            </column>
            <column name="translation_id" type="bigint"/>
            <column name="locale" type="varchar(255)"/>
            <column name="text" type="mediumtext"/>
        </createTable>
        <addUniqueConstraint tableName="translation_medium" columnNames="translation_id,locale"
                constraintName="TRANSLATION_MEDIUM_UNIQUE_TRANSLATION_PER_LANG"/>
        <addForeignKeyConstraint constraintName="TRANSLATION_MEDIUM_TRANSLATION_FK"
                baseTableName="translation_medium" baseColumnNames="translation_id"
                referencedTableName="translation" referencedColumnNames="id"/>
        <createIndex tableName="translation_medium" indexName="TRANSLATION_MEDIUM_LANG_INDEX">
            <column name="locale"/>
        </createIndex>

        <!-- Agents (Correspond to user in Mayocat, but user is a reserved word) -->
        <createTable tableName="agent">
            <column name="entity_id" type="bigint">
                <constraints primaryKey="true" nullable="false"/>
            </column>
            <column name="email" type="varchar(255)">
                <constraints nullable="false"/>
            </column>
            <column name="password" type="varchar(255)"/>
        </createTable>
        <addForeignKeyConstraint constraintName="AGENT_ENTITY_FK"
                baseTableName="agent" baseColumnNames="entity_id"
                referencedTableName="entity" referencedColumnNames="id"/>
        <createIndex tableName="agent" indexName="AGENT_EMAIL_INDEX">
            <column name="email"/>
        </createIndex>

        <!-- Attachments -->
        <createTable tableName="attachment">
            <column name="entity_id" type="bigint">
                <constraints primaryKey="true" nullable="false"/>
            </column>
            <column name="extension" type="varchar(255)">
                <constraints nullable="false"/>
            </column>
            <column name="title" type="varchar(255)"/>
            <column name="description" type="mediumtext"/>
            <column name="data" type="mediumblob"/>
        </createTable>
        <addForeignKeyConstraint constraintName="ATTACHMENT_ENTITY_FK"
                baseTableName="attachment" baseColumnNames="entity_id"
                referencedTableName="entity" referencedColumnNames="id"/>
        <createIndex tableName="attachment" indexName="ATTACHMENT_EXTENSION_INDEX">
            <column name="extension"/>
        </createIndex>

        <!-- Thumbnails -->
        <createTable tableName="thumbnail">
            <column name="attachment_id" type="bigint">
                <constraints nullable="false"/>
            </column>
            <column name="source" type="varchar(255)"/>
            <column name="hint" type="varchar(255)"/>
            <column name="ratio" type="varchar(255)"/>
            <column name="x" type="int"/>
            <column name="y" type="int"/>
            <column name="width" type="int"/>
            <column name="height" type="int"/>
        </createTable>
        <addPrimaryKey tableName="thumbnail"
                columnNames="attachment_id,source,hint" constraintName="THUMBNAIL_PK"/>
        <addForeignKeyConstraint constraintName="THUMBNAIL_IMAGE_FK"
                baseTableName="thumbnail" baseColumnNames="attachment_id"
                referencedTableName="attachment" referencedColumnNames="entity_id"/>
        <createIndex tableName="thumbnail" indexName="THUMBNAIL_HINT_INDEX">
            <column name="hint"/>
        </createIndex>
        <createIndex tableName="thumbnail" indexName="THUMBNAIL_HINT_SOURCE">
            <column name="source"/>
        </createIndex>
        <createIndex tableName="thumbnail" indexName="THUMBNAIL_HINT_RATIO">
            <column name="ratio"/>
        </createIndex>

        <!-- Role table -->
        <createTable tableName="agent_role">
            <column name="id" type="bigint" autoIncrement="true">
                <constraints primaryKey="true" nullable="false"/>
            </column>
            <column name="agent_id" type="bigint"/>
            <column name="role" type="varchar(255)"/>
        </createTable>
        <addForeignKeyConstraint constraintName="AGENT_ROLE_AGENT_KF"
                baseTableName="agent_role" baseColumnNames="agent_id"
                referencedTableName="agent" referencedColumnNames="entity_id"/>

        <!-- Page table -->
        <createTable tableName="page">
            <column name="entity_id" type="bigint">
                <constraints primaryKey="true" nullable="false"/>
            </column>
            <column name="model" type="varchar(255)"/>
            <column name="published" type="boolean"/>
            <column name="position" type="smallint"/>
            <column name="title" type="varchar(255)"/>
            <column name="content" type="mediumtext"/>
            <column name="featured_image_id" type="bigint"/>
        </createTable>
        <addForeignKeyConstraint constraintName="PAGE_ENTITY_FK"
                baseTableName="page" baseColumnNames="entity_id"
                referencedTableName="entity" referencedColumnNames="id"/>
        <addForeignKeyConstraint constraintName="PAGE_FEATURED_IMAGE_FK"
                baseTableName="page" baseColumnNames="featured_image_id"
                referencedTableName="entity" referencedColumnNames="id"/>
        <createIndex tableName="page" indexName="PAGE_POSITION_INDEX">
            <column name="position"/>
        </createIndex>
        <createIndex tableName="page" indexName="PAGE_PUBLISHED_INDEX">
            <column name="published"/>
        </createIndex>

        <!-- News article table -->
        <createTable tableName="article">
            <column name="entity_id" type="bigint">
                <constraints primaryKey="true" nullable="false"/>
            </column>
            <column name="model" type="varchar(255)"/>
            <column name="published" type="boolean"/>
            <column name="publication_date" type="timestamp"/>
            <column name="title" type="varchar(255)"/>
            <column name="content" type="mediumtext"/>
            <column name="featured_image_id" type="bigint"/>
        </createTable>
        <addForeignKeyConstraint constraintName="ARTICLE_ENTITY_FK"
                baseTableName="article" baseColumnNames="entity_id"
                referencedTableName="entity" referencedColumnNames="id"/>
        <addForeignKeyConstraint constraintName="ARTICLE_FEATURED_IMAGE_FK"
                baseTableName="article" baseColumnNames="featured_image_id"
                referencedTableName="entity" referencedColumnNames="id"/>
        <createIndex tableName="article" indexName="ARTICLE_PUBLICATION_DATE_INDEX">
            <column name="publication_date"/>
        </createIndex>
        <createIndex tableName="article" indexName="ARTICLE_PUBLISHED_INDEX">
            <column name="published"/>
        </createIndex>

        <!-- Product table -->
        <createTable tableName="product">
            <column name="entity_id" type="bigint">
                <constraints primaryKey="true" nullable="false"/>
            </column>
            <column name="model" type="varchar(255)"/>
            <column name="on_shelf" type="boolean"/>
            <column name="position" type="smallint"/>
            <column name="title" type="varchar(255)"/>
            <column name="description" type="mediumtext"/>
            <column name="price" type="numeric(18,4)"/>
            <column name="stock" type="smallint"/>
            <column name="featured_image_id" type="bigint"/>
        </createTable>
        <addForeignKeyConstraint constraintName="PRODUCT_ENTITY_FK"
                baseTableName="product" baseColumnNames="entity_id"
                referencedTableName="entity" referencedColumnNames="id"/>
        <addForeignKeyConstraint constraintName="PRODUCT_FEATURED_IMAGE_FK"
                baseTableName="product" baseColumnNames="featured_image_id"
                referencedTableName="entity" referencedColumnNames="id"/>
        <createIndex tableName="product" indexName="PRODUCT_POSITION_INDEX">
            <column name="position"/>
        </createIndex>
        <createIndex tableName="product" indexName="PRODUCT_ON_SHELF_INDEX">
            <column name="on_shelf"/>
        </createIndex>

        <!-- Collection table -->
        <createTable tableName="collection">
            <column name="entity_id" type="bigint">
                <constraints primaryKey="true" nullable="false"/>
            </column>
            <column name="position" type="smallint"/>
            <column name="title" type="varchar(255)"/>
            <column name="description" type="mediumtext"/>
            <column name="featured_image_id" type="bigint"/>
        </createTable>
        <addForeignKeyConstraint constraintName="COLLECTION_ENTITY_FK"
                baseTableName="collection" baseColumnNames="entity_id"
                referencedTableName="entity" referencedColumnNames="id"/>
        <addForeignKeyConstraint constraintName="COLLECTION_FEATURED_IMAGE_FK"
                baseTableName="collection" baseColumnNames="featured_image_id"
                referencedTableName="entity" referencedColumnNames="id"/>
        <createIndex tableName="collection" indexName="COLLECTION_POSITION_INDEX">
            <column name="position"/>
        </createIndex>

        <!-- COLLECTION <-> Product -->
        <createTable tableName="collection_product">
            <column name="collection_id" type="bigint"/>
            <column name="product_id" type="bigint"/>
            <column name="position" type="smallint"/>
        </createTable>
        <addForeignKeyConstraint constraintName="COLLECTION_PRODUCT_COLLECTION_ENTITY_FK"
                baseTableName="collection_product" baseColumnNames="collection_id"
                referencedTableName="entity" referencedColumnNames="id"/>
        <addForeignKeyConstraint constraintName="COLLECTION_PRODUCT_PRODUCT_ENTITY_FK"
                baseTableName="collection_product" baseColumnNames="product_id"
                referencedTableName="entity" referencedColumnNames="id"/>
        <addPrimaryKey tableName="collection_product"
                columnNames="collection_id,product_id" constraintName="COLLECTION_PRODUCT_PK"/>
        <createIndex tableName="collection_product" indexName="COLLECTION_PRODUCT_POSITION_INDEX">
            <column name="position"/>
        </createIndex>

        <!-- Customer table -->
        <createTable tableName="customer">
            <column name="entity_id" type="bigint">
                <constraints primaryKey="true" nullable="false"/>
            </column>
            <column name="email" type="varchar(255)"/>
            <column name="first_name" type="varchar(255)"/>
            <column name="last_name" type="varchar(255)"/>
        </createTable>
        <addForeignKeyConstraint constraintName="CUSTOMER_ENTITY_FK"
                baseTableName="customer" baseColumnNames="entity_id"
                referencedTableName="entity" referencedColumnNames="id"/>
        <createIndex tableName="customer" indexName="CUSTOMER_EMAIL_INDEX">
            <column name="email"/>
        </createIndex>

        <!-- Address table -->
        <createTable tableName="address">
            <column name="address_id" type="bigint" autoIncrement="true">
                <constraints primaryKey="true" nullable="false"/>
            </column>
            <column name="customer_id" type="bigint"/>
            <column name="company" type="varchar(255)"/>
            <column name="full_name" type="varchar(255)"/>
            <column name="street" type="varchar(255)"/>
            <column name="street_complement" type="varchar(255)"/>
            <column name="zip" type="varchar(255)"/>
            <column name="city" type="varchar(255)"/>
            <column name="country" type="varchar(255)"/>
        </createTable>
        <addForeignKeyConstraint constraintName="ADDRESS_CUSTOMER_FK"
                baseTableName="address" baseColumnNames="customer_id"
                referencedTableName="customer" referencedColumnNames="entity_id"/>

        <!-- Orders table -->
        <createTable tableName="purchase_order">
            <column name="entity_id" type="bigint">
                <constraints primaryKey="true" nullable="false"/>
            </column>
            <column name="customer_id" type="bigint"/>
            <column name="delivery_address_id" type="bigint"/>
            <column name="billing_address_id" type="bigint"/>
            <column name="creation_date" type="timestamp"/>
            <column name="update_date" type="timestamp"/>
            <column name="currency" type="varchar(3)"/>
            <column name="number_of_items" type="smallint"/>
            <column name="items_total" type="numeric(18,4)"/>
            <column name="grand_total" type="numeric(18,4)"/>
            <column name="status" type="varchar(32)"/>
            <column name="order_data" type="mediumtext"/>
        </createTable>
        <addForeignKeyConstraint constraintName="ORDER_ENTITY_FK"
                baseTableName="purchase_order" baseColumnNames="entity_id"
                referencedTableName="entity" referencedColumnNames="id"/>
        <addForeignKeyConstraint constraintName="ORDER_CUSTOMER_ENTITY_FK"
                baseTableName="purchase_order" baseColumnNames="customer_id"
                referencedTableName="entity" referencedColumnNames="id"/>
        <addForeignKeyConstraint constraintName="ORDER_DELIVERY_ADDRESS_ENTITY_FK"
                baseTableName="purchase_order" baseColumnNames="delivery_address_id"
                referencedTableName="address" referencedColumnNames="address_id"/>
        <addForeignKeyConstraint constraintName="ORDER_BILLING_ADDRESS_ENTITY_FK"
                baseTableName="purchase_order" baseColumnNames="billing_address_id"
                referencedTableName="address" referencedColumnNames="address_id"/>

    </changeSet>

</databaseChangeLog>
